MoD/MoD.py
MoD/__init__.py
MoD/modeling/__init__.py
MoD/modeling/automodeling.py
MoD/modeling/models/BloomMoD.py
MoD/modeling/models/FalconMoD.py
MoD/modeling/models/GemmaMoD.py
MoD/modeling/models/LlamaMoD.py
MoD/modeling/models/MistralMoD.py
MoD/modeling/models/MixtralMoD.py
MoD/modeling/models/PhiMoD.py
MoD/modeling/models/QwenMoD.py
MoD/modeling/models/QwenMoEMoD.py
MoD/modeling/models/StarCoderMoD.py
MoD/modeling/models/__init__.py
mixture_of_depth-1.2.0.dist-info/METADATA
mixture_of_depth-1.2.0.dist-info/WHEEL
mixture_of_depth-1.2.0.dist-info/top_level.txt
mixture_of_depth-1.2.0.dist-info/RECORD
