Metadata-Version: 2.1
Name: mixture-of-depth
Version: 1.2.0
Summary: Unofficial implementation for the paper "Mixture-of-Depths: Dynamically allocating compute in transformer-based language models"
Home-page: https://github.com/astramind-ai/Mixture-of-depths
Author: Marco Lironi
Author-email: marcolironi@astramind.ai
Classifier: Programming Language :: Python :: 3
Classifier: License :: OSI Approved :: Apache Software License
Classifier: Operating System :: OS Independent
Requires-Python: >=3.6
Requires-Dist: torch
